a_selenium_errorhandler/LICENSE
a_selenium_errorhandler/README.MD
a_selenium_errorhandler/__init__.py
a_selenium_errorhandler/requirements.txt
a_selenium_errorhandler/thirdparty.json
a_selenium_errorhandler-0.10.dist-info/LICENSE.rst
a_selenium_errorhandler-0.10.dist-info/METADATA
a_selenium_errorhandler-0.10.dist-info/WHEEL
a_selenium_errorhandler-0.10.dist-info/top_level.txt
a_selenium_errorhandler-0.10.dist-info/RECORD
